LICENSE.txt
README.md
setup.py
kdotp_symmetry/__init__.py
kdotp_symmetry/_expr_utils.py
kdotp_symmetry/_linalg.py
kdotp_symmetry/_logging_setup.py
kdotp_symmetry/_repr_utils.py
kdotp_symmetry/_symmetric_hamiltonian.py
kdotp_symmetry/_to_matrix.py
kdotp_symmetry.egg-info/PKG-INFO
kdotp_symmetry.egg-info/SOURCES.txt
kdotp_symmetry.egg-info/dependency_links.txt
kdotp_symmetry.egg-info/requires.txt
kdotp_symmetry.egg-info/top_level.txt