Metadata-Version: 2.1
Name: kdotp-symmetry
Version: 1.0.1
Summary: Calculating the general form of a k.p Hamiltonian with given symmetry constraints.
Home-page: http://z2pack.ethz.ch/kdotp-symmetry
Author: Dominik Gresch
Author-email: greschd@gmx.ch
License: Apache 2.0
Platform: UNKNOWN
Classifier: License :: OSI Approved :: Apache Software License
Classifier: Natural Language :: English
Classifier: Operating System :: Unix
Classifier: Programming Language :: Python :: 3
Classifier: Programming Language :: Python :: 3.5
Classifier: Programming Language :: Python :: 3.6
Classifier: Intended Audience :: Science/Research
Classifier: Topic :: Scientific/Engineering :: Physics
Classifier: Development Status :: 4 - Beta
Provides-Extra: dev
